[{"date": "2026-04-01", "open": 37.25, "high": 37.25, "low": 36.6, "close": 36.95, "volume": 27675434}, {"date": "2026-04-02", "open": 37.3, "high": 38.75, "low": 37.05, "close": 38.4, "volume": 61239163}, {"date": "2026-04-07", "open": 38.4, "high": 39.2, "low": 37.65, "close": 38.1, "volume": 40603882}, {"date": "2026-04-08", "open": 38.0, "high": 38.5, "low": 37.7, "close": 38.5, "volume": 29534925}, {"date": "2026-04-09", "open": 38.8, "high": 39.0, "low": 38.25, "close": 38.5, "volume": 24341595}, {"date": "2026-04-10", "open": 38.7, "high": 39.3, "low": 37.6, "close": 37.75, "volume": 35310832}, {"date": "2026-04-13", "open": 38.1, "high": 38.65, "low": 37.9, "close": 38.3, "volume": 16498657}, {"date": "2026-04-14", "open": 38.5, "high": 38.8, "low": 38.1, "close": 38.45, "volume": 25492065}, {"date": "2026-04-15", "open": 38.4, "high": 38.45, "low": 37.3, "close": 37.45, "volume": 30848824}, {"date": "2026-04-16", "open": 37.65, "high": 37.65, "low": 37.2, "close": 37.3, "volume": 14305515}, {"date": "2026-04-17", "open": 37.45, "high": 37.6, "low": 37.3, "close": 37.6, "volume": 11212042}, {"date": "2026-04-20", "open": 37.85, "high": 37.85, "low": 36.9, "close": 36.95, "volume": 21077275}, {"date": "2026-04-21", "open": 37.05, "high": 37.2, "low": 36.75, "close": 36.95, "volume": 11820898}, {"date": "2026-04-22", "open": 37.0, "high": 37.05, "low": 36.55, "close": 36.8, "volume": 18278612}, {"date": "2026-04-23", "open": 36.85, "high": 36.9, "low": 35.9, "close": 36.25, "volume": 29867538}, {"date": "2026-04-24", "open": 36.25, "high": 36.4, "low": 35.9, "close": 36.35, "volume": 13789358}, {"date": "2026-04-27", "open": 36.35, "high": 36.5, "low": 35.9, "close": 36.4, "volume": 13790287}, {"date": "2026-04-28", "open": 36.6, "high": 38.35, "low": 36.6, "close": 38.05, "volume": 37461372}, {"date": "2026-04-29", "open": 38.1, "high": 38.9, "low": 37.65, "close": 38.45, "volume": 37919445}, {"date": "2026-04-30", "open": 38.55, "high": 38.7, "low": 37.6, "close": 37.7, "volume": 20009399}, {"date": "2026-05-04", "open": 38.15, "high": 38.15, "low": 37.6, "close": 37.7, "volume": 10445323}, {"date": "2026-05-05", "open": 37.85, "high": 38.1, "low": 37.45, "close": 37.75, "volume": 10405987}, {"date": "2026-05-06", "open": 38.05, "high": 38.75, "low": 37.75, "close": 38.45, "volume": 31091906}, {"date": "2026-05-08", "open": 39.1, "high": 39.8, "low": 38.65, "close": 39.6, "volume": 33348864}, {"date": "2026-05-11", "open": 40.0, "high": 40.45, "low": 39.5, "close": 39.95, "volume": 30077425}, {"date": "2026-05-12", "open": 40.2, "high": 40.25, "low": 39.4, "close": 39.7, "volume": 23834355}, {"date": "2026-05-13", "open": 39.05, "high": 39.05, "low": 37.6, "close": 38.1, "volume": 40973530}, {"date": "2026-05-14", "open": 38.25, "high": 40.5, "low": 38.1, "close": 39.8, "volume": 57508095}, {"date": "2026-05-15", "open": 40.05, "high": 41.2, "low": 39.75, "close": 39.85, "volume": 47747482}, {"date": "2026-05-18", "open": 39.5, "high": 41.0, "low": 39.25, "close": 39.4, "volume": 37468752}, {"date": "2026-05-19", "open": 39.5, "high": 40.35, "low": 39.35, "close": 40.0, "volume": 25955528}, {"date": "2026-05-20", "open": 40.3, "high": 41.95, "low": 40.25, "close": 41.15, "volume": 46970650}, {"date": "2026-05-21", "open": 41.35, "high": 42.45, "low": 40.85, "close": 42.35, "volume": 34914027}, {"date": "2026-05-22", "open": 42.5, "high": 42.9, "low": 41.75, "close": 41.95, "volume": 24351187}, {"date": "2026-05-25", "open": 42.5, "high": 44.35, "low": 42.5, "close": 43.8, "volume": 37622473}, {"date": "2026-05-27", "open": 41.5, "high": 43.25, "low": 41.05, "close": 42.45, "volume": 27210094}, {"date": "2026-05-28", "open": 42.55, "high": 43.15, "low": 41.4, "close": 41.75, "volume": 18913490}, {"date": "2026-05-29", "open": 42.15, "high": 42.5, "low": 41.6, "close": 41.65, "volume": 17386615}, {"date": "2026-06-01", "open": 42.05, "high": 43.2, "low": 41.6, "close": 43.2, "volume": 28077068}, {"date": "2026-06-02", "open": 43.6, "high": 43.65, "low": 42.05, "close": 43.65, "volume": 33817082}, {"date": "2026-06-03", "open": 43.35, "high": 44.35, "low": 42.2, "close": 43.85, "volume": 35447430}, {"date": "2026-06-04", "open": 43.8, "high": 44.2, "low": 43.35, "close": 44.1, "volume": 26108921}, {"date": "2026-06-05", "open": 44.5, "high": 44.5, "low": 43.35, "close": 43.8, "volume": 22945418}, {"date": "2026-06-08", "open": 41.5, "high": 42.2, "low": 40.6, "close": 41.8, "volume": 35147056}, {"date": "2026-06-09", "open": 41.85, "high": 43.4, "low": 41.85, "close": 42.9, "volume": 26474849}, {"date": "2026-06-10", "open": 42.6, "high": 43.55, "low": 42.35, "close": 42.5, "volume": 21898479}, {"date": "2026-06-11", "open": 42.1, "high": 42.55, "low": 41.65, "close": 42.55, "volume": 21682577}, {"date": "2026-06-12", "open": 43.35, "high": 44.05, "low": 42.85, "close": 43.55, "volume": 15120012}, {"date": "2026-06-16", "open": 43.25, "high": 43.3, "low": 41.1, "close": 41.7, "volume": 34528826}, {"date": "2026-06-17", "open": 41.45, "high": 42.0, "low": 40.9, "close": 41.7, "volume": 16814322}, {"date": "2026-06-18", "open": 41.5, "high": 42.1, "low": 40.8, "close": 41.0, "volume": 22472299}, {"date": "2026-06-22", "open": 41.0, "high": 42.0, "low": 40.85, "close": 41.1, "volume": 14737337}, {"date": "2026-06-23", "open": 41.55, "high": 41.7, "low": 40.0, "close": 40.0, "volume": 17997024}, {"date": "2026-06-24", "open": 39.9, "high": 40.6, "low": 39.6, "close": 40.55, "volume": 8623384}, {"date": "2026-06-25", "open": 40.7, "high": 41.3, "low": 40.2, "close": 40.2, "volume": 10687839}, {"date": "2026-06-26", "open": 40.0, "high": 40.45, "low": 39.5, "close": 39.9, "volume": 16797163}, {"date": "2026-06-29", "open": 40.3, "high": 40.7, "low": 39.75, "close": 40.4, "volume": 8928643}, {"date": "2026-06-30", "open": 40.5, "high": 40.65, "low": 40.1, "close": 40.35, "volume": 10148303}, {"date": "2026-07-01", "open": 40.5, "high": 41.9, "low": 39.55, "close": 41.5, "volume": 50528170}, {"date": "2026-07-02", "open": 41.0, "high": 41.4, "low": 40.45, "close": 40.65, "volume": 14678216}, {"date": "2026-07-03", "open": 40.45, "high": 41.3, "low": 40.45, "close": 41.15, "volume": 7403959}, {"date": "2026-07-06", "open": 41.15, "high": 41.65, "low": 41.1, "close": 41.3, "volume": 7065493}, {"date": "2026-07-07", "open": 41.25, "high": 41.65, "low": 40.9, "close": 40.9, "volume": 11863125}, {"date": "2026-07-08", "open": 41.2, "high": 41.5, "low": 40.15, "close": 40.55, "volume": 7440910}, {"date": "2026-07-09", "open": 40.8, "high": 41.0, "low": 40.0, "close": 40.0, "volume": 10877312}, {"date": "2026-07-13", "open": 40.1, "high": 40.25, "low": 39.35, "close": 39.5, "volume": 20528143}, {"date": "2026-07-14", "open": 38.45, "high": 39.2, "low": 38.2, "close": 39.1, "volume": 17214567}, {"date": "2026-07-15", "open": 39.5, "high": 41.6, "low": 39.3, "close": 41.3, "volume": 23957921}, {"date": "2026-07-16", "open": 41.2, "high": 41.4, "low": 40.35, "close": 41.0, "volume": 9243874}, {"date": "2026-07-17", "open": 40.65, "high": 41.6, "low": 40.4, "close": 40.65, "volume": 15766038}, {"date": "2026-07-20", "open": 40.95, "high": 41.35, "low": 40.05, "close": 40.45, "volume": 10955143}, {"date": "2026-07-21", "open": 40.5, "high": 41.3, "low": 40.5, "close": 41.15, "volume": 10093057}]