[{"date": "2026-04-01", "open": 20.75, "high": 20.85, "low": 20.7, "close": 20.75, "volume": 10598745}, {"date": "2026-04-02", "open": 20.85, "high": 20.9, "low": 20.7, "close": 20.75, "volume": 6542119}, {"date": "2026-04-07", "open": 20.8, "high": 21.1, "low": 20.7, "close": 21.1, "volume": 15855627}, {"date": "2026-04-08", "open": 21.15, "high": 21.15, "low": 20.95, "close": 21.0, "volume": 11267459}, {"date": "2026-04-09", "open": 21.05, "high": 21.1, "low": 20.9, "close": 21.05, "volume": 6540669}, {"date": "2026-04-10", "open": 21.15, "high": 21.15, "low": 20.95, "close": 21.1, "volume": 7665911}, {"date": "2026-04-13", "open": 20.9, "high": 20.95, "low": 20.7, "close": 20.75, "volume": 15394866}, {"date": "2026-04-14", "open": 20.75, "high": 20.75, "low": 20.6, "close": 20.7, "volume": 14962646}, {"date": "2026-04-15", "open": 20.75, "high": 20.75, "low": 20.6, "close": 20.7, "volume": 7507529}, {"date": "2026-04-16", "open": 20.75, "high": 20.85, "low": 20.6, "close": 20.65, "volume": 9215122}, {"date": "2026-04-17", "open": 20.75, "high": 20.75, "low": 20.5, "close": 20.55, "volume": 16483445}, {"date": "2026-04-20", "open": 20.6, "high": 20.65, "low": 20.4, "close": 20.5, "volume": 13171065}, {"date": "2026-04-21", "open": 20.55, "high": 20.55, "low": 20.3, "close": 20.4, "volume": 14935455}, {"date": "2026-04-22", "open": 20.4, "high": 20.4, "low": 20.25, "close": 20.35, "volume": 15026746}, {"date": "2026-04-23", "open": 20.35, "high": 20.35, "low": 20.15, "close": 20.15, "volume": 22785987}, {"date": "2026-04-24", "open": 20.0, "high": 20.05, "low": 19.8, "close": 19.95, "volume": 31975757}, {"date": "2026-04-27", "open": 19.8, "high": 19.85, "low": 19.6, "close": 19.8, "volume": 27710202}, {"date": "2026-04-28", "open": 19.8, "high": 20.1, "low": 19.6, "close": 20.1, "volume": 12052520}, {"date": "2026-04-29", "open": 20.15, "high": 20.15, "low": 19.9, "close": 20.0, "volume": 7860331}, {"date": "2026-04-30", "open": 20.0, "high": 20.05, "low": 19.75, "close": 19.85, "volume": 12995569}, {"date": "2026-05-04", "open": 19.85, "high": 19.95, "low": 19.8, "close": 19.8, "volume": 14606899}, {"date": "2026-05-05", "open": 19.8, "high": 19.8, "low": 19.7, "close": 19.8, "volume": 13724186}, {"date": "2026-05-06", "open": 19.8, "high": 19.8, "low": 19.65, "close": 19.75, "volume": 16516759}, {"date": "2026-05-08", "open": 19.85, "high": 19.95, "low": 19.75, "close": 19.75, "volume": 14905785}, {"date": "2026-05-11", "open": 19.8, "high": 19.8, "low": 19.65, "close": 19.75, "volume": 13989928}, {"date": "2026-05-12", "open": 19.8, "high": 19.8, "low": 19.6, "close": 19.6, "volume": 16289285}, {"date": "2026-05-13", "open": 19.45, "high": 19.45, "low": 19.3, "close": 19.45, "volume": 28174558}, {"date": "2026-05-14", "open": 19.3, "high": 19.4, "low": 18.9, "close": 19.0, "volume": 47828257}, {"date": "2026-05-15", "open": 18.95, "high": 18.95, "low": 18.55, "close": 18.75, "volume": 47741218}, {"date": "2026-05-18", "open": 18.55, "high": 18.9, "low": 18.5, "close": 18.85, "volume": 21964043}, {"date": "2026-05-19", "open": 18.85, "high": 19.3, "low": 18.7, "close": 19.15, "volume": 16848788}, {"date": "2026-05-20", "open": 19.15, "high": 19.15, "low": 18.9, "close": 18.9, "volume": 10579347}, {"date": "2026-05-21", "open": 18.95, "high": 19.05, "low": 18.9, "close": 19.0, "volume": 7968092}, {"date": "2026-05-22", "open": 19.0, "high": 19.05, "low": 18.9, "close": 18.95, "volume": 9345144}, {"date": "2026-05-25", "open": 19.0, "high": 19.0, "low": 18.75, "close": 18.75, "volume": 13345189}, {"date": "2026-05-27", "open": 18.85, "high": 18.9, "low": 18.7, "close": 18.8, "volume": 16571442}, {"date": "2026-05-28", "open": 18.8, "high": 18.8, "low": 18.5, "close": 18.5, "volume": 26000156}, {"date": "2026-05-29", "open": 18.5, "high": 18.6, "low": 18.4, "close": 18.45, "volume": 18546027}, {"date": "2026-06-01", "open": 18.45, "high": 18.45, "low": 18.1, "close": 18.4, "volume": 41743083}, {"date": "2026-06-02", "open": 18.35, "high": 18.75, "low": 18.25, "close": 18.7, "volume": 18764721}, {"date": "2026-06-03", "open": 18.75, "high": 19.4, "low": 18.7, "close": 19.25, "volume": 27278741}, {"date": "2026-06-04", "open": 19.35, "high": 19.65, "low": 19.25, "close": 19.4, "volume": 29039373}, {"date": "2026-06-05", "open": 19.45, "high": 19.55, "low": 19.15, "close": 19.3, "volume": 20260580}, {"date": "2026-06-08", "open": 18.8, "high": 19.1, "low": 18.6, "close": 19.05, "volume": 21697134}, {"date": "2026-06-09", "open": 19.05, "high": 19.75, "low": 19.05, "close": 19.7, "volume": 24967617}, {"date": "2026-06-10", "open": 19.6, "high": 19.65, "low": 19.3, "close": 19.4, "volume": 18308641}, {"date": "2026-06-11", "open": 19.3, "high": 19.3, "low": 19.05, "close": 19.2, "volume": 12756792}, {"date": "2026-06-12", "open": 19.35, "high": 19.65, "low": 19.35, "close": 19.5, "volume": 13229252}, {"date": "2026-06-16", "open": 19.7, "high": 19.9, "low": 19.55, "close": 19.75, "volume": 20585737}, {"date": "2026-06-17", "open": 19.85, "high": 20.15, "low": 19.8, "close": 19.85, "volume": 27486457}, {"date": "2026-06-18", "open": 19.95, "high": 20.1, "low": 19.8, "close": 19.8, "volume": 22418129}, {"date": "2026-06-22", "open": 20.0, "high": 20.0, "low": 19.6, "close": 19.65, "volume": 14702604}, {"date": "2026-06-23", "open": 19.65, "high": 20.1, "low": 19.6, "close": 20.0, "volume": 19416862}, {"date": "2026-06-24", "open": 19.9, "high": 20.0, "low": 19.75, "close": 19.85, "volume": 11532691}, {"date": "2026-06-25", "open": 19.85, "high": 20.1, "low": 19.8, "close": 20.05, "volume": 15546101}, {"date": "2026-06-26", "open": 19.95, "high": 20.05, "low": 19.75, "close": 19.8, "volume": 13316439}, {"date": "2026-06-29", "open": 19.8, "high": 20.0, "low": 19.8, "close": 19.95, "volume": 7124996}, {"date": "2026-06-30", "open": 20.0, "high": 20.05, "low": 19.85, "close": 20.05, "volume": 15088187}, {"date": "2026-07-01", "open": 20.05, "high": 20.1, "low": 19.85, "close": 19.9, "volume": 9335974}, {"date": "2026-07-02", "open": 19.9, "high": 20.15, "low": 19.8, "close": 20.15, "volume": 11214729}, {"date": "2026-07-03", "open": 20.15, "high": 20.6, "low": 20.15, "close": 20.4, "volume": 18851526}, {"date": "2026-07-06", "open": 20.5, "high": 20.7, "low": 20.4, "close": 20.55, "volume": 11040653}, {"date": "2026-07-07", "open": 20.6, "high": 20.8, "low": 20.55, "close": 20.65, "volume": 15527585}, {"date": "2026-07-08", "open": 20.7, "high": 20.75, "low": 20.45, "close": 20.6, "volume": 7737126}, {"date": "2026-07-09", "open": 20.65, "high": 20.75, "low": 20.55, "close": 20.6, "volume": 7010244}, {"date": "2026-07-13", "open": 20.6, "high": 20.8, "low": 20.5, "close": 20.65, "volume": 8851324}, {"date": "2026-07-14", "open": 20.75, "high": 20.75, "low": 20.2, "close": 20.5, "volume": 15875601}, {"date": "2026-07-15", "open": 20.45, "high": 20.6, "low": 20.2, "close": 20.3, "volume": 14811357}, {"date": "2026-07-16", "open": 20.3, "high": 20.45, "low": 20.2, "close": 20.25, "volume": 14709032}, {"date": "2026-07-17", "open": 20.25, "high": 20.55, "low": 20.2, "close": 20.55, "volume": 31205183}, {"date": "2026-07-20", "open": 20.55, "high": 20.65, "low": 20.1, "close": 20.35, "volume": 24689553}, {"date": "2026-07-21", "open": 20.4, "high": 20.6, "low": 20.4, "close": 20.45, "volume": 31543014}, {"date": "2026-07-22", "open": 20.5, "high": 20.6, "low": 20.35, "close": 20.45, "volume": 19850214}, {"date": "2026-07-23", "open": 20.45, "high": 20.55, "low": 20.35, "close": 20.45, "volume": 15890714}, {"date": "2026-07-24", "open": 20.35, "high": 20.5, "low": 20.3, "close": 20.45, "volume": 10356767}]