[{"date": "2026-04-01", "open": 17.2, "high": 18.0, "low": 17.0, "close": 17.95, "volume": 316660}, {"date": "2026-04-02", "open": 17.9, "high": 18.0, "low": 17.6, "close": 17.95, "volume": 151424}, {"date": "2026-04-07", "open": 17.95, "high": 18.0, "low": 17.8, "close": 17.95, "volume": 74401}, {"date": "2026-04-08", "open": 17.85, "high": 18.1, "low": 17.85, "close": 18.1, "volume": 151907}, {"date": "2026-04-09", "open": 18.1, "high": 18.1, "low": 17.85, "close": 18.1, "volume": 60835}, {"date": "2026-04-10", "open": 18.1, "high": 19.25, "low": 18.1, "close": 19.15, "volume": 367836}, {"date": "2026-04-13", "open": 19.1, "high": 19.3, "low": 18.85, "close": 19.2, "volume": 199479}, {"date": "2026-04-14", "open": 19.25, "high": 20.0, "low": 19.25, "close": 20.0, "volume": 525528}, {"date": "2026-04-15", "open": 20.0, "high": 20.45, "low": 19.8, "close": 20.0, "volume": 483098}, {"date": "2026-04-16", "open": 20.0, "high": 20.3, "low": 19.65, "close": 20.05, "volume": 286643}, {"date": "2026-04-17", "open": 20.2, "high": 20.2, "low": 19.4, "close": 19.9, "volume": 226046}, {"date": "2026-04-20", "open": 20.05, "high": 20.05, "low": 19.4, "close": 20.0, "volume": 144892}, {"date": "2026-04-21", "open": 19.95, "high": 20.0, "low": 19.55, "close": 20.0, "volume": 145371}, {"date": "2026-04-22", "open": 20.05, "high": 20.05, "low": 19.15, "close": 19.55, "volume": 225799}, {"date": "2026-04-23", "open": 19.4, "high": 19.75, "low": 18.6, "close": 18.8, "volume": 201159}, {"date": "2026-04-24", "open": 19.0, "high": 19.65, "low": 19.0, "close": 19.2, "volume": 104069}, {"date": "2026-04-27", "open": 19.25, "high": 19.25, "low": 19.0, "close": 19.2, "volume": 111867}, {"date": "2026-04-28", "open": 19.2, "high": 19.5, "low": 19.0, "close": 19.5, "volume": 125684}, {"date": "2026-04-29", "open": 19.7, "high": 19.8, "low": 19.4, "close": 19.8, "volume": 105315}, {"date": "2026-04-30", "open": 20.0, "high": 20.3, "low": 19.75, "close": 19.9, "volume": 145694}, {"date": "2026-05-04", "open": 19.9, "high": 19.9, "low": 19.5, "close": 19.6, "volume": 36730}, {"date": "2026-05-05", "open": 19.35, "high": 19.4, "low": 19.0, "close": 19.1, "volume": 29589}, {"date": "2026-05-06", "open": 19.6, "high": 19.6, "low": 19.1, "close": 19.3, "volume": 64913}, {"date": "2026-05-08", "open": 19.1, "high": 19.15, "low": 18.95, "close": 19.05, "volume": 52078}, {"date": "2026-05-11", "open": 19.05, "high": 19.25, "low": 18.95, "close": 19.0, "volume": 72236}, {"date": "2026-05-12", "open": 18.7, "high": 18.7, "low": 17.95, "close": 18.0, "volume": 142617}, {"date": "2026-05-13", "open": 17.9, "high": 18.0, "low": 17.6, "close": 18.0, "volume": 47860}, {"date": "2026-05-14", "open": 18.0, "high": 18.6, "low": 16.85, "close": 16.85, "volume": 205788}, {"date": "2026-05-15", "open": 16.85, "high": 17.4, "low": 16.55, "close": 16.65, "volume": 138342}, {"date": "2026-05-18", "open": 17.05, "high": 17.1, "low": 16.35, "close": 16.45, "volume": 86780}, {"date": "2026-05-19", "open": 16.75, "high": 16.75, "low": 16.7, "close": 16.7, "volume": 12414}, {"date": "2026-05-20", "open": 16.7, "high": 17.05, "low": 16.4, "close": 17.0, "volume": 99967}, {"date": "2026-05-21", "open": 17.5, "high": 17.5, "low": 17.1, "close": 17.25, "volume": 31762}, {"date": "2026-05-22", "open": 17.0, "high": 17.65, "low": 17.0, "close": 17.35, "volume": 54286}, {"date": "2026-05-25", "open": 17.35, "high": 17.35, "low": 16.8, "close": 16.9, "volume": 47628}, {"date": "2026-05-27", "open": 17.1, "high": 17.15, "low": 16.85, "close": 17.0, "volume": 43353}, {"date": "2026-05-28", "open": 17.3, "high": 17.35, "low": 16.85, "close": 17.1, "volume": 29493}, {"date": "2026-05-29", "open": 17.15, "high": 17.35, "low": 17.1, "close": 17.1, "volume": 172750}, {"date": "2026-06-01", "open": 17.35, "high": 17.65, "low": 17.0, "close": 17.4, "volume": 78606}, {"date": "2026-06-02", "open": 17.0, "high": 17.5, "low": 17.0, "close": 17.45, "volume": 58123}, {"date": "2026-06-03", "open": 17.45, "high": 17.5, "low": 17.15, "close": 17.25, "volume": 36857}, {"date": "2026-06-04", "open": 17.15, "high": 17.45, "low": 17.1, "close": 17.2, "volume": 31627}, {"date": "2026-06-05", "open": 17.2, "high": 17.2, "low": 16.9, "close": 16.9, "volume": 49574}, {"date": "2026-06-08", "open": 16.2, "high": 17.4, "low": 16.2, "close": 16.4, "volume": 104262}, {"date": "2026-06-09", "open": 16.25, "high": 16.35, "low": 16.15, "close": 16.35, "volume": 114322}, {"date": "2026-06-10", "open": 16.05, "high": 16.8, "low": 16.0, "close": 16.7, "volume": 148772}, {"date": "2026-06-11", "open": 16.7, "high": 17.45, "low": 16.7, "close": 17.25, "volume": 117775}, {"date": "2026-06-12", "open": 17.15, "high": 17.2, "low": 17.1, "close": 17.2, "volume": 28962}, {"date": "2026-06-16", "open": 18.05, "high": 18.05, "low": 17.4, "close": 17.4, "volume": 57178}, {"date": "2026-06-17", "open": 17.25, "high": 17.35, "low": 16.95, "close": 17.0, "volume": 51728}, {"date": "2026-06-18", "open": 17.15, "high": 17.35, "low": 17.05, "close": 17.2, "volume": 37922}, {"date": "2026-06-22", "open": 17.05, "high": 17.2, "low": 16.95, "close": 17.15, "volume": 92255}, {"date": "2026-06-23", "open": 17.15, "high": 17.3, "low": 17.0, "close": 17.25, "volume": 46804}, {"date": "2026-06-24", "open": 17.1, "high": 18.15, "low": 17.1, "close": 17.45, "volume": 80118}, {"date": "2026-06-25", "open": 17.55, "high": 17.55, "low": 17.35, "close": 17.5, "volume": 11770}, {"date": "2026-06-26", "open": 17.1, "high": 17.1, "low": 16.4, "close": 16.4, "volume": 60040}, {"date": "2026-06-29", "open": 16.5, "high": 16.65, "low": 16.25, "close": 16.3, "volume": 60583}, {"date": "2026-06-30", "open": 16.6, "high": 16.6, "low": 16.6, "close": 16.6, "volume": 5211}, {"date": "2026-07-01", "open": 16.9, "high": 17.2, "low": 16.65, "close": 16.8, "volume": 44544}, {"date": "2026-07-02", "open": 16.85, "high": 16.85, "low": 16.55, "close": 16.6, "volume": 44826}, {"date": "2026-07-03", "open": 16.9, "high": 17.0, "low": 16.9, "close": 17.0, "volume": 4950}, {"date": "2026-07-06", "open": 17.0, "high": 17.0, "low": 16.65, "close": 16.85, "volume": 30657}, {"date": "2026-07-07", "open": 16.8, "high": 16.85, "low": 16.65, "close": 16.85, "volume": 29100}, {"date": "2026-07-08", "open": 16.8, "high": 16.9, "low": 16.65, "close": 16.65, "volume": 49253}, {"date": "2026-07-09", "open": 16.6, "high": 16.9, "low": 16.55, "close": 16.85, "volume": 16211}, {"date": "2026-07-13", "open": 17.0, "high": 17.2, "low": 16.8, "close": 17.1, "volume": 57404}, {"date": "2026-07-14", "open": 17.15, "high": 17.15, "low": 16.75, "close": 17.15, "volume": 65579}, {"date": "2026-07-15", "open": 17.2, "high": 18.6, "low": 17.15, "close": 18.5, "volume": 140222}, {"date": "2026-07-16", "open": 18.75, "high": 18.75, "low": 17.6, "close": 17.95, "volume": 61021}, {"date": "2026-07-17", "open": 17.5, "high": 18.0, "low": 17.5, "close": 18.0, "volume": 81027}, {"date": "2026-07-20", "open": 18.25, "high": 19.15, "low": 18.2, "close": 18.55, "volume": 218914}, {"date": "2026-07-21", "open": 18.85, "high": 18.85, "low": 18.1, "close": 18.45, "volume": 47163}, {"date": "2026-07-22", "open": 18.2, "high": 18.25, "low": 17.5, "close": 17.75, "volume": 61813}, {"date": "2026-07-23", "open": 17.65, "high": 18.0, "low": 17.6, "close": 18.0, "volume": 19418}, {"date": "2026-07-24", "open": 17.65, "high": 17.95, "low": 17.35, "close": 17.95, "volume": 49010}]